cfgs.py
cfgs-0.13.0.dist-info/LICENSE
cfgs-0.13.0.dist-info/METADATA
cfgs-0.13.0.dist-info/WHEEL
cfgs-0.13.0.dist-info/RECORD
